pathwayParameterAdvising/__init__.py
pathwayParameterAdvising/getReactomePaths.py
pathwayParameterAdvising/graphletUtils.py
pathwayParameterAdvising/makePGDNet.py
pathwayParameterAdvising/ppa.py
pathwayParameterAdvising-0.2.0.dist-info/METADATA
pathwayParameterAdvising-0.2.0.dist-info/WHEEL
pathwayParameterAdvising-0.2.0.dist-info/top_level.txt
pathwayParameterAdvising-0.2.0.dist-info/RECORD
