Metadata-Version: 2.1
Name: pathwayParameterAdvising
Version: 0.2.0
Summary: Parameter advising for biological pathway reconstruction algorithms.
Home-page: https://github.com/gitter-lab/pathway-parameter-advising
Author: Chris Magnano
Author-email: chrismagnano@gmail.com
License: UNKNOWN
Keywords: pathway-finding parameter-advising pathway-reconstruction biological-pathway graphlet
Platform: UNKNOWN
Classifier: Development Status :: 4 - Beta
Classifier: Intended Audience :: Science/Research
Classifier: Topic :: Scientific/Engineering :: Bio-Informatics
Classifier: License :: OSI Approved :: MIT License
Classifier: Programming Language :: Python :: 3
Classifier: Programming Language :: Python :: 3 :: Only
Classifier: Programming Language :: Python :: 3.6
Classifier: License :: OSI Approved :: MIT License
Classifier: Operating System :: Unix 
Classifier: Operating System :: MacOS :: MacOS X
Requires-Python: >=3.6
Requires-Dist: numpy
Requires-Dist: networkx
Requires-Dist: requests
